libname/__init__.py
libname/hello.py
bsmote-0.0.1.dist-info/METADATA
bsmote-0.0.1.dist-info/WHEEL
bsmote-0.0.1.dist-info/top_level.txt
bsmote-0.0.1.dist-info/RECORD
